README.rst
setup.py
freekey/__init__.py
freekey/daemon.py
freekey/freekey.py
freekey/pyxhook.py
freekey.egg-info/PKG-INFO
freekey.egg-info/SOURCES.txt
freekey.egg-info/dependency_links.txt
freekey.egg-info/top_level.txt