Metadata-Version: 1.1
Name: freekey
Version: 0.1.3
Summary: Allows limited keyboard use on a locked desktop
Home-page: https://github.com/chrisspen/freekey
Author: Chris Spencer
Author-email: chrisspen@gmail.com
License: LGPL
Platform: Linux
Classifier: Programming Language :: Python
Classifier: Development Status :: 3 - Alpha
Classifier: Intended Audience :: Developers
Classifier: License :: OSI Approved :: GNU Library or Lesser General Public License (LGPL)
Classifier: Topic :: Software Development :: Libraries :: Python Modules
